README.md
setup.cfg
setup.py
movie_dylan/Play_movie.py
movie_dylan/__init__.py
movie_dylan.egg-info/PKG-INFO
movie_dylan.egg-info/SOURCES.txt
movie_dylan.egg-info/dependency_links.txt
movie_dylan.egg-info/requires.txt
movie_dylan.egg-info/top_level.txt