Metadata-Version: 2.1
Name: movie-dylan
Version: 0.0.1
Summary: test pypi
Home-page: https://lidelin@git.netsdl.com/lidelin/Movie
Author: Dylan
Author-email: lidelin@netsdl.com
License: UNKNOWN
Keywords: Movie python
Platform: UNKNOWN
Classifier: Programming Language :: Python :: 3
Classifier: License :: OSI Approved :: MIT License
Classifier: Operating System :: OS Independent
